{
    "ModGenericComponent": {
                                "DisplayNameLocalizationId" : "GAMEPLAY_PlanterSmall",
                                "DescriptionLocalizatonId" : "GAMEPLAY_PlanterSmallDescription",
                                "InventoryActionLocalizationId" : "",
                                "WeightKG": 0.20,
                                "DaysToDecay" : 0,
                                "MaxHP" : 100,
                                "InitialCondition" : "Perfect",
                                "InventoryCategory" : "Tool",
                                "PickUpAudio" : "PLAY_TINCANFULLPICKUP",
                                "PutBackAudio" : "PLAY_TINCANFULLPUTDOWN",
                                "StowAudio" : "Play_InventoryStow",
                                "WornOutAudio" : "",
                                "InspectOnPickup" : true,
                                "InspectDistance" : 0.5,
                                "InspectAngles" : [-30, 0, 0],
                                "InspectOffset" : [0, -0.1, 0],
                                "InspectScale" :  [1, 1, 1],
                                "NormalModel" : "",
                                "InspectModel" : ""
                            }
}